MANIFEST.in
setup.py
RQmargin.egg-info/PKG-INFO
RQmargin.egg-info/SOURCES.txt
RQmargin.egg-info/dependency_links.txt
RQmargin.egg-info/not-zip-safe
RQmargin.egg-info/requires.txt
RQmargin.egg-info/top_level.txt
rqmargin/__init__.py
rqmargin/config.json
rqmargin/config.py
rqmargin/fetch/__init__.py
rqmargin/fetch/fetching.py
rqmargin/handle/__init__.py
rqmargin/handle/handling.py
rqmargin/store/__init__.py
rqmargin/store/mongosave.py
rqmargin/store/store.py
rqmargin/test/__init__.py
rqmargin/test/update_margin_details.py
rqmargin/test/update_margins.py