Metadata-Version: 1.0
Name: RQmargin
Version: 0.1.27
Summary: fetch and store RQmargin data into mongodb.
Home-page: http://www.ricequant.com
Author: ricequant
Author-email: public@ricequant.com
License: UNKNOWN
Platform: UNKNOWN
